cnsenti/__init__.py
cnsenti/emotion.py
cnsenti/sentiment.py
cnsenti/dictionary/dutir/乐.pkl
cnsenti/dictionary/dutir/哀.pkl
cnsenti/dictionary/dutir/好.pkl
cnsenti/dictionary/dutir/怒.pkl
cnsenti/dictionary/dutir/恶.pkl
cnsenti/dictionary/dutir/惊.pkl
cnsenti/dictionary/dutir/惧.pkl
cnsenti/dictionary/hownet/deny.pkl
cnsenti/dictionary/hownet/extreme.pkl
cnsenti/dictionary/hownet/ish.pkl
cnsenti/dictionary/hownet/more.pkl
cnsenti/dictionary/hownet/neg.pkl
cnsenti/dictionary/hownet/pos.pkl
cnsenti/dictionary/hownet/very.pkl
cnsenti-0.0.6.dist-info/LICENSE
cnsenti-0.0.6.dist-info/METADATA
cnsenti-0.0.6.dist-info/WHEEL
cnsenti-0.0.6.dist-info/top_level.txt
cnsenti-0.0.6.dist-info/RECORD
