Metadata-Version: 2.1
Name: cnsenti
Version: 0.0.6
Summary: 中文情感分析库(Chinese Sentiment))可对文本进行情绪分析、正负情感分析。
Home-page: https://github.com/thunderhit/eventextraction
Author: 大邓
Author-email: thunderhit@qq.com
License: MIT
Keywords: chinese text analysis,text analysis,sentiment,sentiment analysis,natural language processing
Platform: UNKNOWN
Requires-Python: >=3.5
Requires-Dist: jieba
Requires-Dist: numpy
